attune/__init__.py
attune/agent_monitoring.py
attune/cache_monitor.py
attune/cache_stats.py
attune/cli_legacy.py
attune/cli_minimal.py
attune/cli_router.py
attune/cli_unified.py
attune/config.py
attune/coordination.py
attune/core.py
attune/cost_tracker.py
attune/discovery.py
attune/emergence.py
attune/exceptions.py
attune/feedback_loops.py
attune/levels.py
attune/leverage_points.py
attune/logging_config.py
attune/pattern_cache.py
attune/pattern_library.py
attune/persistence.py
attune/platform_utils.py
attune/redis_config.py
attune/redis_memory.py
attune/templates.py
attune/tier_recommender.py
attune/tools.py
attune/trust_building.py
attune/vscode_bridge.py
attune/workflow_commands.py
attune/adaptive/__init__.py
attune/adaptive/task_complexity.py
attune/cache/__init__.py
attune/cache/base.py
attune/cache/dependency_manager.py
attune/cache/hash_only.py
attune/cache/hybrid.py
attune/cache/storage.py
attune/cli/__init__.py
attune/cli/__main__.py
attune/cli/core.py
attune/cli/commands/__init__.py
attune/cli/commands/batch.py
attune/cli/commands/cache.py
attune/cli/commands/help.py
attune/cli/commands/info.py
attune/cli/commands/inspect.py
attune/cli/commands/inspection.py
attune/cli/commands/memory.py
attune/cli/commands/metrics.py
attune/cli/commands/orchestrate.py
attune/cli/commands/patterns.py
attune/cli/commands/profiling.py
attune/cli/commands/provider.py
attune/cli/commands/routing.py
attune/cli/commands/setup.py
attune/cli/commands/status.py
attune/cli/commands/sync.py
attune/cli/commands/tier.py
attune/cli/commands/utilities.py
attune/cli/commands/workflow.py
attune/cli/parsers/__init__.py
attune/cli/parsers/batch.py
attune/cli/parsers/cache.py
attune/cli/parsers/help.py
attune/cli/parsers/info.py
attune/cli/parsers/inspect.py
attune/cli/parsers/metrics.py
attune/cli/parsers/orchestrate.py
attune/cli/parsers/patterns.py
attune/cli/parsers/provider.py
attune/cli/parsers/routing.py
attune/cli/parsers/setup.py
attune/cli/parsers/status.py
attune_ai-2.0.2.dist-info/licenses/LICENSE
attune_ai-2.0.2.dist-info/licenses/LICENSE_CHANGE_ANNOUNCEMENT.md
attune_ai-2.0.2.dist-info/METADATA
attune_ai-2.0.2.dist-info/WHEEL
attune_ai-2.0.2.dist-info/entry_points.txt
attune_ai-2.0.2.dist-info/top_level.txt
attune_ai-2.0.2.dist-info/RECORD
