Metadata-Version: 2.4
Name: attune-ai
Version: 2.0.2
Summary: AI collaboration framework with real LLM agent execution, AskUserQuestion tool integration, Socratic agent generation, progressive tier escalation (70-85% cost savings), meta-orchestration, dynamic agent composition (10 patterns including Anthropic-inspired), intelligent caching (85% hit rate), semantic workflow discovery, visual workflow editor, MCP integration for Claude Code, and multi-agent orchestration.
Author-email: Patrick Roebuck <admin@smartaimemory.com>
Maintainer-email: Smart-AI-Memory <admin@smartaimemory.com>
License:                                  Apache License
Project-URL: Homepage, https://www.smartaimemory.com
Project-URL: Documentation, https://www.smartaimemory.com/framework-docs/
Project-URL: Getting Started, https://www.smartaimemory.com/framework-docs/tutorials/quickstart/
Project-URL: FAQ, https://www.smartaimemory.com/framework-docs/reference/FAQ/
Project-URL: Book, https://www.smartaimemory.com/book
Project-URL: Repository, https://github.com/Smart-AI-Memory/attune-ai
Project-URL: Issues, https://github.com/Smart-AI-Memory/attune-ai/issues
Project-URL: Discussions, https://github.com/Smart-AI-Memory/attune-ai/discussions
Project-URL: Changelog, https://github.com/Smart-AI-Memory/attune-ai/blob/main/CHANGELOG.md
Keywords: ai,collaboration,empathy,anticipatory-ai,systems-thinking,llm,claude,memdocs,level-5-ai,code-inspection,static-analysis,code-quality,sarif,github-actions,developer-tools
Classifier: Development Status :: 5 - Production/Stable
Classifier: Intended Audience :: Developers
Classifier: License :: OSI Approved :: Apache Software License
Classifier: Topic :: Software Development :: Libraries :: Application Frameworks
Classifier: Topic :: Scientific/Engineering :: Artificial Intelligence
Classifier: Programming Language :: Python :: 3
Classifier: Programming Language :: Python :: 3.10
Classifier: Programming Language :: Python :: 3.11
Classifier: Programming Language :: Python :: 3.12
Classifier: Programming Language :: Python :: 3.13
Classifier: Operating System :: OS Independent
Requires-Python: >=3.10
License-File: LICENSE
License-File: LICENSE_CHANGE_ANNOUNCEMENT.md
Requires-Dist: pydantic<3.0.0,>=2.0.0
Requires-Dist: typing-extensions<5.0.0,>=4.0.0
Requires-Dist: python-dotenv<2.0.0,>=1.0.0
Requires-Dist: structlog<26.0.0,>=23.0.0
Requires-Dist: defusedxml<1.0.0,>=0.7.0
Requires-Dist: rich<14.0.0,>=13.0.0
Requires-Dist: typer<1.0.0,>=0.9.0
Requires-Dist: pyyaml<7.0,>=6.0
Requires-Dist: anthropic<1.0.0,>=0.25.0
Provides-Extra: anthropic
Requires-Dist: anthropic<1.0.0,>=0.25.0; extra == "anthropic"
Provides-Extra: openai
Requires-Dist: openai<2.0.0,>=1.12.0; extra == "openai"
Provides-Extra: google
Requires-Dist: google-generativeai<1.0.0,>=0.3.0; extra == "google"
Provides-Extra: llm
Requires-Dist: anthropic<1.0.0,>=0.25.0; extra == "llm"
Requires-Dist: openai<2.0.0,>=1.12.0; extra == "llm"
Requires-Dist: google-generativeai<1.0.0,>=0.3.0; extra == "llm"
Provides-Extra: memdocs
Requires-Dist: memdocs>=1.0.0; extra == "memdocs"
Provides-Extra: agents
Requires-Dist: langchain<2.0.0,>=1.0.0; extra == "agents"
Requires-Dist: langchain-core<2.0.0,>=1.2.5; extra == "agents"
Requires-Dist: langchain-text-splitters<0.4.0,>=0.3.9; extra == "agents"
Requires-Dist: langgraph<2.0.0,>=1.0.0; extra == "agents"
Requires-Dist: langgraph-checkpoint<4.0.0,>=3.0.0; extra == "agents"
Requires-Dist: marshmallow<5.0.0,>=4.1.2; extra == "agents"
Provides-Extra: crewai
Requires-Dist: crewai<1.0.0,>=0.1.0; extra == "crewai"
Requires-Dist: langchain<2.0.0,>=0.1.0; extra == "crewai"
Requires-Dist: langchain-core<2.0.0,>=1.2.6; extra == "crewai"
Provides-Extra: cache
Requires-Dist: sentence-transformers<4.0.0,>=2.0.0; extra == "cache"
Requires-Dist: torch<3.0.0,>=2.0.0; extra == "cache"
Requires-Dist: numpy<3.0.0,>=1.24.0; extra == "cache"
Provides-Extra: healthcare
Requires-Dist: anthropic<1.0.0,>=0.25.0; extra == "healthcare"
Requires-Dist: openai<2.0.0,>=1.12.0; extra == "healthcare"
Requires-Dist: google-generativeai<1.0.0,>=0.3.0; extra == "healthcare"
Requires-Dist: memdocs>=1.0.0; extra == "healthcare"
Requires-Dist: langchain<2.0.0,>=1.0.0; extra == "healthcare"
Requires-Dist: langchain-core<2.0.0,>=1.2.5; extra == "healthcare"
Requires-Dist: langchain-text-splitters<0.4.0,>=0.3.9; extra == "healthcare"
Requires-Dist: langgraph<2.0.0,>=1.0.0; extra == "healthcare"
Requires-Dist: langgraph-checkpoint<4.0.0,>=3.0.0; extra == "healthcare"
Requires-Dist: marshmallow<5.0.0,>=4.1.2; extra == "healthcare"
Requires-Dist: python-docx<1.0.0,>=0.8.11; extra == "healthcare"
Requires-Dist: pyyaml<7.0,>=6.0; extra == "healthcare"
Requires-Dist: fastapi<1.0.0,>=0.109.1; extra == "healthcare"
Requires-Dist: uvicorn<1.0.0,>=0.20.0; extra == "healthcare"
Requires-Dist: starlette<1.0.0,>=0.40.0; extra == "healthcare"
Requires-Dist: bcrypt<5.0.0,>=4.0.0; extra == "healthcare"
Requires-Dist: PyJWT[crypto]>=2.8.0; extra == "healthcare"
Requires-Dist: opentelemetry-api<2.0.0,>=1.20.0; extra == "healthcare"
Requires-Dist: opentelemetry-sdk<2.0.0,>=1.20.0; extra == "healthcare"
Requires-Dist: opentelemetry-exporter-otlp-proto-grpc<2.0.0,>=1.20.0; extra == "healthcare"
Requires-Dist: redis<6.0.0,>=5.0.0; extra == "healthcare"
Provides-Extra: software
Requires-Dist: python-docx<1.0.0,>=0.8.11; extra == "software"
Requires-Dist: pyyaml<7.0,>=6.0; extra == "software"
Provides-Extra: backend
Requires-Dist: fastapi<1.0.0,>=0.109.1; extra == "backend"
Requires-Dist: uvicorn<1.0.0,>=0.20.0; extra == "backend"
Requires-Dist: starlette<1.0.0,>=0.40.0; extra == "backend"
Requires-Dist: bcrypt<5.0.0,>=4.0.0; extra == "backend"
Requires-Dist: PyJWT[crypto]>=2.8.0; extra == "backend"
Provides-Extra: lsp
Requires-Dist: pygls<2.0.0,>=1.0.0; extra == "lsp"
Requires-Dist: lsprotocol<2024.0.0,>=2023.0.0; extra == "lsp"
Provides-Extra: windows
Requires-Dist: colorama<1.0.0,>=0.4.6; extra == "windows"
Provides-Extra: otel
Requires-Dist: opentelemetry-api<2.0.0,>=1.20.0; extra == "otel"
Requires-Dist: opentelemetry-sdk<2.0.0,>=1.20.0; extra == "otel"
Requires-Dist: opentelemetry-exporter-otlp-proto-grpc<2.0.0,>=1.20.0; extra == "otel"
Provides-Extra: docs
Requires-Dist: mkdocs<2.0.0,>=1.5.0; extra == "docs"
Requires-Dist: mkdocs-material<10.0.0,>=9.4.0; extra == "docs"
Requires-Dist: mkdocstrings[python]<1.0.0,>=0.24.0; extra == "docs"
Requires-Dist: mkdocs-with-pdf<1.0.0,>=0.9.3; extra == "docs"
Requires-Dist: pymdown-extensions<11.0,>=10.0; extra == "docs"
Provides-Extra: dev
Requires-Dist: pytest<10.0,>=7.0; extra == "dev"
Requires-Dist: pytest-asyncio<2.0,>=0.21; extra == "dev"
Requires-Dist: pytest-cov<8.0,>=4.0; extra == "dev"
Requires-Dist: pytest-mock<4.0,>=3.14.0; extra == "dev"
Requires-Dist: pytest-xdist<4.0,>=3.5.0; extra == "dev"
Requires-Dist: pytest-testmon<3.0,>=2.1.0; extra == "dev"
Requires-Dist: pytest-picked<1.0,>=0.5.0; extra == "dev"
Requires-Dist: black<27.0,>=24.3.0; extra == "dev"
Requires-Dist: mypy<2.0,>=1.0; extra == "dev"
Requires-Dist: ruff<1.0,>=0.1; extra == "dev"
Requires-Dist: coverage<8.0,>=7.0; extra == "dev"
Requires-Dist: bandit<2.0,>=1.7; extra == "dev"
Requires-Dist: pre-commit<5.0,>=3.0; extra == "dev"
Requires-Dist: httpx<1.0.0,>=0.27.0; extra == "dev"
Requires-Dist: fastapi<1.0.0,>=0.109.1; extra == "dev"
Requires-Dist: requests<3.0.0,>=2.28.0; extra == "dev"
Provides-Extra: developer
Requires-Dist: anthropic<1.0.0,>=0.25.0; extra == "developer"
Requires-Dist: openai<2.0.0,>=1.12.0; extra == "developer"
Requires-Dist: google-generativeai<1.0.0,>=0.3.0; extra == "developer"
Requires-Dist: memdocs>=1.0.0; extra == "developer"
Requires-Dist: langchain<2.0.0,>=1.0.0; extra == "developer"
Requires-Dist: langchain-core<2.0.0,>=1.2.5; extra == "developer"
Requires-Dist: langchain-text-splitters<0.4.0,>=0.3.9; extra == "developer"
Requires-Dist: langgraph<2.0.0,>=1.0.0; extra == "developer"
Requires-Dist: langgraph-checkpoint<4.0.0,>=3.0.0; extra == "developer"
Requires-Dist: marshmallow<5.0.0,>=4.1.2; extra == "developer"
Requires-Dist: python-docx<1.0.0,>=0.8.11; extra == "developer"
Requires-Dist: pyyaml<7.0,>=6.0; extra == "developer"
Provides-Extra: enterprise
Requires-Dist: anthropic<1.0.0,>=0.25.0; extra == "enterprise"
Requires-Dist: openai<2.0.0,>=1.12.0; extra == "enterprise"
Requires-Dist: google-generativeai<1.0.0,>=0.3.0; extra == "enterprise"
Requires-Dist: memdocs>=1.0.0; extra == "enterprise"
Requires-Dist: langchain<2.0.0,>=1.0.0; extra == "enterprise"
Requires-Dist: langchain-core<2.0.0,>=1.2.5; extra == "enterprise"
Requires-Dist: langchain-text-splitters<0.4.0,>=0.3.9; extra == "enterprise"
Requires-Dist: langgraph<2.0.0,>=1.0.0; extra == "enterprise"
Requires-Dist: langgraph-checkpoint<4.0.0,>=3.0.0; extra == "enterprise"
Requires-Dist: marshmallow<5.0.0,>=4.1.2; extra == "enterprise"
Requires-Dist: python-docx<1.0.0,>=0.8.11; extra == "enterprise"
Requires-Dist: pyyaml<7.0,>=6.0; extra == "enterprise"
Requires-Dist: fastapi<1.0.0,>=0.109.1; extra == "enterprise"
Requires-Dist: uvicorn<1.0.0,>=0.20.0; extra == "enterprise"
Requires-Dist: starlette<1.0.0,>=0.40.0; extra == "enterprise"
Requires-Dist: bcrypt<5.0.0,>=4.0.0; extra == "enterprise"
Requires-Dist: PyJWT[crypto]>=2.8.0; extra == "enterprise"
Requires-Dist: opentelemetry-api<2.0.0,>=1.20.0; extra == "enterprise"
Requires-Dist: opentelemetry-sdk<2.0.0,>=1.20.0; extra == "enterprise"
Requires-Dist: opentelemetry-exporter-otlp-proto-grpc<2.0.0,>=1.20.0; extra == "enterprise"
Provides-Extra: full
Requires-Dist: anthropic<1.0.0,>=0.25.0; extra == "full"
Requires-Dist: openai<2.0.0,>=1.12.0; extra == "full"
Requires-Dist: google-generativeai<1.0.0,>=0.3.0; extra == "full"
Requires-Dist: memdocs>=1.0.0; extra == "full"
Requires-Dist: langchain<2.0.0,>=1.0.0; extra == "full"
Requires-Dist: langchain-core<2.0.0,>=1.2.5; extra == "full"
Requires-Dist: langchain-text-splitters<0.4.0,>=0.3.9; extra == "full"
Requires-Dist: langgraph<2.0.0,>=1.0.0; extra == "full"
Requires-Dist: langgraph-checkpoint<4.0.0,>=3.0.0; extra == "full"
Requires-Dist: marshmallow<5.0.0,>=4.1.2; extra == "full"
Requires-Dist: python-docx<1.0.0,>=0.8.11; extra == "full"
Requires-Dist: pyyaml<7.0,>=6.0; extra == "full"
Provides-Extra: all
Requires-Dist: anthropic<1.0.0,>=0.25.0; extra == "all"
Requires-Dist: openai<2.0.0,>=1.12.0; extra == "all"
Requires-Dist: google-generativeai<1.0.0,>=0.3.0; extra == "all"
Requires-Dist: memdocs>=1.0.0; extra == "all"
Requires-Dist: langchain<2.0.0,>=1.0.0; extra == "all"
Requires-Dist: langchain-core<2.0.0,>=1.2.5; extra == "all"
Requires-Dist: langchain-text-splitters<0.4.0,>=0.3.9; extra == "all"
Requires-Dist: langgraph<2.0.0,>=1.0.0; extra == "all"
Requires-Dist: langgraph-checkpoint<4.0.0,>=3.0.0; extra == "all"
Requires-Dist: marshmallow<5.0.0,>=4.1.2; extra == "all"
Requires-Dist: python-docx<1.0.0,>=0.8.11; extra == "all"
Requires-Dist: pyyaml<7.0,>=6.0; extra == "all"
Requires-Dist: fastapi<1.0.0,>=0.109.1; extra == "all"
Requires-Dist: uvicorn<1.0.0,>=0.20.0; extra == "all"
Requires-Dist: starlette<1.0.0,>=0.40.0; extra == "all"
Requires-Dist: bcrypt<5.0.0,>=4.0.0; extra == "all"
Requires-Dist: PyJWT[crypto]>=2.8.0; extra == "all"
Requires-Dist: pygls<2.0.0,>=1.0.0; extra == "all"
Requires-Dist: lsprotocol<2024.0.0,>=2023.0.0; extra == "all"
Requires-Dist: colorama<1.0.0,>=0.4.6; extra == "all"
Requires-Dist: opentelemetry-api<2.0.0,>=1.20.0; extra == "all"
Requires-Dist: opentelemetry-sdk<2.0.0,>=1.20.0; extra == "all"
Requires-Dist: opentelemetry-exporter-otlp-proto-grpc<2.0.0,>=1.20.0; extra == "all"
Requires-Dist: mkdocs<2.0.0,>=1.5.0; extra == "all"
Requires-Dist: mkdocs-material<10.0.0,>=9.4.0; extra == "all"
Requires-Dist: mkdocstrings[python]<1.0.0,>=0.24.0; extra == "all"
Requires-Dist: mkdocs-with-pdf<1.0.0,>=0.9.3; extra == "all"
Requires-Dist: pymdown-extensions<11.0,>=10.0; extra == "all"
Requires-Dist: pytest<10.0,>=7.0; extra == "all"
Requires-Dist: pytest-asyncio<2.0,>=0.21; extra == "all"
Requires-Dist: pytest-cov<8.0,>=4.0; extra == "all"
Requires-Dist: black<27.0,>=24.3.0; extra == "all"
Requires-Dist: mypy<2.0,>=1.0; extra == "all"
Requires-Dist: ruff<1.0,>=0.1; extra == "all"
Requires-Dist: coverage<8.0,>=7.0; extra == "all"
Requires-Dist: bandit<2.0,>=1.7; extra == "all"
Requires-Dist: pre-commit<5.0,>=3.0; extra == "all"
Requires-Dist: httpx<1.0.0,>=0.27.0; extra == "all"
Requires-Dist: urllib3<3.0.0,>=2.3.0; extra == "all"
Requires-Dist: aiohttp<4.0.0,>=3.10.0; extra == "all"
Requires-Dist: filelock<4.0.0,>=3.16.0; extra == "all"
Dynamic: license-file
